seed/__init__.py
seed/baseparser.py
seed/exceptions.py
seed/run.py
seed/utilities.py
seed/commands/__init__.py
seed/commands/create.py
seed/commands/help.py
seed/commands/release.py
seed/vcs/__init__.py
seed/vcs/git.py
seed/vcs/github.py
seed-0.11.3.dist-info/DESCRIPTION.rst
seed-0.11.3.dist-info/entry_points.txt
seed-0.11.3.dist-info/METADATA
seed-0.11.3.dist-info/metadata.json
seed-0.11.3.dist-info/RECORD
seed-0.11.3.dist-info/top_level.txt
seed-0.11.3.dist-info/WHEEL
seed_tests/__init__.py
seed_tests/test_create.py
seed_tests/test_help.py
seed_tests/test_release.py
