Metadata-Version: 2.0
Name: seed
Version: 0.11.3
Summary: A utility for easily creating and releasing Python packages
Home-page: https://github.com/adamcharnock/seed
Author: Adam Charnock
Author-email: adam@adamcharnock.com
License: MIT
Platform: UNKNOWN
Classifier: Environment :: Console
Classifier: Intended Audience :: Developers
Classifier: License :: OSI Approved :: MIT License
Classifier: Operating System :: OS Independent
Classifier: Programming Language :: Python
Classifier: Programming Language :: Python :: 2.7
Classifier: Programming Language :: Python :: 3.4
Classifier: Programming Language :: Python :: 3.5
Classifier: Topic :: System :: Software Distribution
Requires-Dist: path.py (>=10,<11)
Requires-Dist: wheel
